gbart/__init__.py
gbart/create_dataset.py
gbart/groupbart.py
gbart/utilities.py
gbart/modified_bartpy/data.py
gbart/modified_bartpy/errors.py
gbart/modified_bartpy/featureimportance.py
gbart/modified_bartpy/featureselection.py
gbart/modified_bartpy/model.py
gbart/modified_bartpy/mutation.py
gbart/modified_bartpy/node.py
gbart/modified_bartpy/plotting.py
gbart/modified_bartpy/runner.py
gbart/modified_bartpy/sigma.py
gbart/modified_bartpy/sklearnmodel.py
gbart/modified_bartpy/split.py
gbart/modified_bartpy/trace.py
gbart/modified_bartpy/tree.py
gbart/modified_bartpy/diagnostics/__init__.py
gbart/modified_bartpy/diagnostics/features.py
gbart/modified_bartpy/diagnostics/residuals.py
gbart/modified_bartpy/diagnostics/trees.py
gbart/modified_bartpy/extensions/__init__.py
gbart/modified_bartpy/extensions/baseestimator.py
gbart/modified_bartpy/extensions/ols.py
gbart/modified_bartpy/samplers/__init__.py
gbart/modified_bartpy/samplers/leafnode.py
gbart/modified_bartpy/samplers/modelsampler.py
gbart/modified_bartpy/samplers/sampler.py
gbart/modified_bartpy/samplers/schedule.py
gbart/modified_bartpy/samplers/sigma.py
gbart/modified_bartpy/samplers/treemutation/__init__.py
gbart/modified_bartpy/samplers/treemutation/likihoodratio.py
gbart/modified_bartpy/samplers/treemutation/proposer.py
gbart/modified_bartpy/samplers/treemutation/treemutation.py
gbart/modified_bartpy/samplers/treemutation/uniform/__init__.py
gbart/modified_bartpy/samplers/treemutation/uniform/likihoodratio.py
gbart/modified_bartpy/samplers/treemutation/uniform/proposer.py
gbart-0.2.1.dist-info/LICENSE
gbart-0.2.1.dist-info/METADATA
gbart-0.2.1.dist-info/WHEEL
gbart-0.2.1.dist-info/top_level.txt
gbart-0.2.1.dist-info/RECORD
