Metadata-Version: 2.1
Name: gbart
Version: 0.2.1
Summary: A python package to implement Variable Grouping Based Bayesian Additive Regression Tree, associated with ICASSP2020 submitted paper
Home-page: https://github.com/AugusHsu/gbart
Author: Yuhao Su, Jie Ding
Author-email: su000088@umn.edu, dingj@umn.edu
License: UNKNOWN
Platform: UNKNOWN
Classifier: Programming Language :: Python :: 3
Classifier: License :: OSI Approved :: MIT License
Classifier: Operating System :: OS Independent
Requires-Python: >=3.6
Requires-Dist: joblib
Requires-Dist: matplotlib
Requires-Dist: numpy
Requires-Dist: pandas
Requires-Dist: scipy
Requires-Dist: seaborn
Requires-Dist: sklearn
Requires-Dist: statsmodels
